sanji/message.py
sanji/__init__.py
sanji/model_initiator.py
sanji/bundle.py
sanji/config.py
sanji/session.py
sanji/publish.py
sanji/router.py
sanji/core.py
sanji/connection/mockup.py
sanji/connection/__init__.py
sanji/connection/connection.py
sanji/connection/mqtt.py
sanji-0.0.1.dist-info/METADATA
sanji-0.0.1.dist-info/metadata.json
sanji-0.0.1.dist-info/WHEEL
sanji-0.0.1.dist-info/RECORD
sanji-0.0.1.dist-info/top_level.txt
sanji-0.0.1.dist-info/DESCRIPTION.rst
