Metadata-Version: 2.0
Name: sanji
Version: 0.0.1
Summary: Sanji Framework SDK
Home-page: https://github.com/Sanji-IO/sanji
Author: Sanji Team
Author-email: sanji@moxa.com
License: MIT
Platform: UNKNOWN
Classifier: Development Status :: 5 - Production/Stable
Classifier: Intended Audience :: Developers
Classifier: Natural Language :: English
Classifier: License :: OSI Approved :: MIT License
Classifier: Operating System :: OS Independent
Classifier: Programming Language :: Python
Classifier: Programming Language :: Python :: 2
Classifier: Programming Language :: Python :: 2.6
Classifier: Programming Language :: Python :: 2.7
Classifier: Topic :: Software Development :: Libraries :: Python Modules
Requires-Dist: voluptuous
